{
    "model_name": "PML-PPMS",
    "project_url": "https://pubs.acs.org/doi/abs/10.1021/acs.nanolett.2c04420",
    "date_submitted": "01-14-2023",
    "author_email": "adam.biacchi@nist.gov",
    "database_version": "12-12-2022",
    "team_name": "PML-PPMS",
    "time_taken_seconds": {
        "EXP-SinglePropertyPrediction-Tc_supercon_JVASP_1151_MgB2-dft_3d-test-mae.csv.zip": ""
    },
    "language": "python",
    "os": "linux",
    "software_used": "jarvis-tools",
    "hardware_used": "Magnetization-PPMS",
    "git_url": []
}